flask_cors-stubs/METADATA.toml
flask_cors-stubs/__init__.pyi
flask_cors-stubs/core.pyi
flask_cors-stubs/decorator.pyi
flask_cors-stubs/extension.pyi
flask_cors-stubs/py.typed
flask_cors-stubs/version.pyi
types_flask_cors-6.0.0.20250520.dist-info/licenses/LICENSE
types_flask_cors-6.0.0.20250520.dist-info/METADATA
types_flask_cors-6.0.0.20250520.dist-info/WHEEL
types_flask_cors-6.0.0.20250520.dist-info/top_level.txt
types_flask_cors-6.0.0.20250520.dist-info/RECORD
